<?xml version="1.0" encoding="UTF-8"?>
<DEFECTS>
  <DEFECT>
    <SFA>
      <FILEPATH>c:\users\akshaya balamurugan\desktop\clipsnet_vs_2015\clipsclrwrapper\source\clips\</FILEPATH>
      <FILENAME>exprnpsr.c</FILENAME>
      <LINE>296</LINE>
      <COLUMN>44</COLUMN>
    </SFA>
    <DEFECTCODE>6011</DEFECTCODE>
    <DESCRIPTION>Dereferencing NULL pointer 'theFunction'. </DESCRIPTION>
    <FUNCTION>Function2Parse</FUNCTION>
    <DECORATED>?Function2Parse@@$$FYAPAUexpr@@PAXPBD1@Z</DECORATED>
    <FUNCLINE>147</FUNCLINE>
    <PROBABILITY>1</PROBABILITY>
    <RANK>4</RANK>
    <CATEGORY>
      <RULECATEGORY>mspft</RULECATEGORY>
    </CATEGORY>
    <PATH>
      <SFA>
        <FILEPATH>c:\users\akshaya balamurugan\desktop\clipsnet_vs_2015\clipsclrwrapper\source\clips\</FILEPATH>
        <FILENAME>exprnpsr.c</FILENAME>
        <LINE>152</LINE>
        <COLUMN>30</COLUMN>
      </SFA>
      <SFA>
        <FILEPATH>c:\users\akshaya balamurugan\desktop\clipsnet_vs_2015\clipsclrwrapper\source\clips\</FILEPATH>
        <FILENAME>exprnpsr.c</FILENAME>
        <LINE>153</LINE>
        <COLUMN>16</COLUMN>
      </SFA>
      <SFA>
        <FILEPATH>c:\users\akshaya balamurugan\desktop\clipsnet_vs_2015\clipsclrwrapper\source\clips\</FILEPATH>
        <FILENAME>exprnpsr.c</FILENAME>
        <LINE>154</LINE>
        <COLUMN>7</COLUMN>
      </SFA>
      <SFA>
        <FILEPATH>c:\users\akshaya balamurugan\desktop\clipsnet_vs_2015\clipsclrwrapper\source\clips\</FILEPATH>
        <FILENAME>exprnpsr.c</FILENAME>
        <LINE>155</LINE>
        <COLUMN>12</COLUMN>
      </SFA>
      <SFA>
        <FILEPATH>c:\users\akshaya balamurugan\desktop\clipsnet_vs_2015\clipsclrwrapper\source\clips\</FILEPATH>
        <FILENAME>exprnpsr.c</FILENAME>
        <LINE>156</LINE>
        <COLUMN>25</COLUMN>
      </SFA>
      <SFA>
        <FILEPATH>c:\users\akshaya balamurugan\desktop\clipsnet_vs_2015\clipsclrwrapper\source\clips\</FILEPATH>
        <FILENAME>exprnpsr.c</FILENAME>
        <LINE>156</LINE>
        <COLUMN>45</COLUMN>
      </SFA>
      <SFA>
        <FILEPATH>c:\users\akshaya balamurugan\desktop\clipsnet_vs_2015\clipsclrwrapper\source\clips\</FILEPATH>
        <FILENAME>exprnpsr.c</FILENAME>
        <LINE>158</LINE>
        <COLUMN>9</COLUMN>
      </SFA>
      <SFA>
        <FILEPATH>c:\users\akshaya balamurugan\desktop\clipsnet_vs_2015\clipsclrwrapper\source\clips\</FILEPATH>
        <FILENAME>exprnpsr.c</FILENAME>
        <LINE>161</LINE>
        <COLUMN>9</COLUMN>
      </SFA>
      <SFA>
        <FILEPATH>c:\users\akshaya balamurugan\desktop\clipsnet_vs_2015\clipsclrwrapper\source\clips\</FILEPATH>
        <FILENAME>exprnpsr.c</FILENAME>
        <LINE>168</LINE>
        <COLUMN>46</COLUMN>
      </SFA>
      <SFA>
        <FILEPATH>c:\users\akshaya balamurugan\desktop\clipsnet_vs_2015\clipsclrwrapper\source\clips\</FILEPATH>
        <FILENAME>exprnpsr.c</FILENAME>
        <LINE>179</LINE>
        <COLUMN>15</COLUMN>
      </SFA>
      <SFA>
        <FILEPATH>c:\users\akshaya balamurugan\desktop\clipsnet_vs_2015\clipsclrwrapper\source\clips\</FILEPATH>
        <FILENAME>exprnpsr.c</FILENAME>
        <LINE>182</LINE>
        <COLUMN>7</COLUMN>
      </SFA>
      <SFA>
        <FILEPATH>c:\users\akshaya balamurugan\desktop\clipsnet_vs_2015\clipsclrwrapper\source\clips\</FILEPATH>
        <FILENAME>exprnpsr.c</FILENAME>
        <LINE>191</LINE>
        <COLUMN>13</COLUMN>
      </SFA>
      <SFA>
        <FILEPATH>c:\users\akshaya balamurugan\desktop\clipsnet_vs_2015\clipsclrwrapper\source\clips\</FILEPATH>
        <FILENAME>exprnpsr.c</FILENAME>
        <LINE>197</LINE>
        <COLUMN>8</COLUMN>
        <KEYEVENT>
          <ID>1</ID>
          <KIND>branch</KIND>
          <IMPORTANCE>Full</IMPORTANCE>
          <MESSAGE>'theFunction' may be NULL (Skip this branch)</MESSAGE>
        </KEYEVENT>
      </SFA>
      <SFA>
        <FILEPATH>c:\users\akshaya balamurugan\desktop\clipsnet_vs_2015\clipsclrwrapper\source\clips\</FILEPATH>
        <FILENAME>exprnpsr.c</FILENAME>
        <LINE>212</LINE>
        <COLUMN>10</COLUMN>
      </SFA>
      <SFA>
        <FILEPATH>c:\users\akshaya balamurugan\desktop\clipsnet_vs_2015\clipsclrwrapper\source\clips\</FILEPATH>
        <FILENAME>exprnpsr.c</FILENAME>
        <LINE>220</LINE>
        <COLUMN>12</COLUMN>
        <KEYEVENT>
          <ID>2</ID>
          <KIND>branch</KIND>
          <IMPORTANCE>Full</IMPORTANCE>
          <MESSAGE>Skip this branch, (assume 'dptr!=0' is false)</MESSAGE>
        </KEYEVENT>
      </SFA>
      <SFA>
        <FILEPATH>c:\users\akshaya balamurugan\desktop\clipsnet_vs_2015\clipsclrwrapper\source\clips\</FILEPATH>
        <FILENAME>exprnpsr.c</FILENAME>
        <LINE>225</LINE>
        <COLUMN>13</COLUMN>
        <KEYEVENT>
          <ID>3</ID>
          <KIND>branch</KIND>
          <IMPORTANCE>Full</IMPORTANCE>
          <MESSAGE>Enter this branch, (assume 'gfunc!=0')</MESSAGE>
        </KEYEVENT>
      </SFA>
      <SFA>
        <FILEPATH>c:\users\akshaya balamurugan\desktop\clipsnet_vs_2015\clipsclrwrapper\source\clips\</FILEPATH>
        <FILENAME>exprnpsr.c</FILENAME>
        <LINE>226</LINE>
        <COLUMN>9</COLUMN>
      </SFA>
      <SFA>
        <FILEPATH>c:\users\akshaya balamurugan\desktop\clipsnet_vs_2015\clipsclrwrapper\source\clips\</FILEPATH>
        <FILENAME>exprnpsr.c</FILENAME>
        <LINE>244</LINE>
        <COLUMN>21</COLUMN>
      </SFA>
      <SFA>
        <FILEPATH>c:\users\akshaya balamurugan\desktop\clipsnet_vs_2015\clipsclrwrapper\source\clips\</FILEPATH>
        <FILENAME>exprnpsr.c</FILENAME>
        <LINE>245</LINE>
        <COLUMN>41</COLUMN>
      </SFA>
      <SFA>
        <FILEPATH>c:\users\akshaya balamurugan\desktop\clipsnet_vs_2015\clipsclrwrapper\source\clips\</FILEPATH>
        <FILENAME>exprnpsr.c</FILENAME>
        <LINE>246</LINE>
        <COLUMN>40</COLUMN>
      </SFA>
      <SFA>
        <FILEPATH>c:\users\akshaya balamurugan\desktop\clipsnet_vs_2015\clipsclrwrapper\source\clips\</FILEPATH>
        <FILENAME>exprnpsr.c</FILENAME>
        <LINE>249</LINE>
        <COLUMN>17</COLUMN>
        <KEYEVENT>
          <ID>4</ID>
          <KIND>branch</KIND>
          <IMPORTANCE>Full</IMPORTANCE>
          <MESSAGE>Skip this branch, (assume 'top-&gt;type==30' is false)</MESSAGE>
        </KEYEVENT>
      </SFA>
      <SFA>
        <FILEPATH>c:\users\akshaya balamurugan\desktop\clipsnet_vs_2015\clipsclrwrapper\source\clips\</FILEPATH>
        <FILENAME>exprnpsr.c</FILENAME>
        <LINE>271</LINE>
        <COLUMN>7</COLUMN>
      </SFA>
      <SFA>
        <FILEPATH>c:\users\akshaya balamurugan\desktop\clipsnet_vs_2015\clipsclrwrapper\source\clips\</FILEPATH>
        <FILENAME>exprnpsr.c</FILENAME>
        <LINE>272</LINE>
        <COLUMN>20</COLUMN>
      </SFA>
      <SFA>
        <FILEPATH>c:\users\akshaya balamurugan\desktop\clipsnet_vs_2015\clipsclrwrapper\source\clips\</FILEPATH>
        <FILENAME>exprnpsr.c</FILENAME>
        <LINE>273</LINE>
        <COLUMN>11</COLUMN>
        <KEYEVENT>
          <ID>5</ID>
          <KIND>branch</KIND>
          <IMPORTANCE>Full</IMPORTANCE>
          <MESSAGE>Skip this branch, (assume 'top==0' is false)</MESSAGE>
        </KEYEVENT>
      </SFA>
      <SFA>
        <FILEPATH>c:\users\akshaya balamurugan\desktop\clipsnet_vs_2015\clipsclrwrapper\source\clips\</FILEPATH>
        <FILENAME>exprnpsr.c</FILENAME>
        <LINE>275</LINE>
        <COLUMN>34</COLUMN>
        <KEYEVENT>
          <ID>6</ID>
          <KIND>branch</KIND>
          <IMPORTANCE>Full</IMPORTANCE>
          <MESSAGE>Skip this branch, (assume '&lt;branch condition&gt;' is false)</MESSAGE>
        </KEYEVENT>
      </SFA>
      <SFA>
        <FILEPATH>c:\users\akshaya balamurugan\desktop\clipsnet_vs_2015\clipsclrwrapper\source\clips\</FILEPATH>
        <FILENAME>exprnpsr.c</FILENAME>
        <LINE>287</LINE>
        <COLUMN>18</COLUMN>
        <KEYEVENT>
          <ID>7</ID>
          <KIND>branch</KIND>
          <IMPORTANCE>Full</IMPORTANCE>
          <MESSAGE>Skip this branch, (assume '&lt;branch condition&gt;' is false)</MESSAGE>
        </KEYEVENT>
      </SFA>
      <SFA>
        <FILEPATH>c:\users\akshaya balamurugan\desktop\clipsnet_vs_2015\clipsclrwrapper\source\clips\</FILEPATH>
        <FILENAME>exprnpsr.c</FILENAME>
        <LINE>294</LINE>
        <COLUMN>28</COLUMN>
        <KEYEVENT>
          <ID>8</ID>
          <KIND>branch</KIND>
          <IMPORTANCE>Full</IMPORTANCE>
          <MESSAGE>Enter this branch, (assume '&lt;branch condition&gt;')</MESSAGE>
        </KEYEVENT>
      </SFA>
      <SFA>
        <FILEPATH>c:\users\akshaya balamurugan\desktop\clipsnet_vs_2015\clipsclrwrapper\source\clips\</FILEPATH>
        <FILENAME>exprnpsr.c</FILENAME>
        <LINE>296</LINE>
        <COLUMN>44</COLUMN>
        <KEYEVENT>
          <ID>9</ID>
          <KIND>branch</KIND>
          <IMPORTANCE>Full</IMPORTANCE>
          <MESSAGE>Skip this branch, (assume '&lt;branch condition&gt;' is false)</MESSAGE>
        </KEYEVENT>
      </SFA>
      <SFA>
        <FILEPATH>c:\users\akshaya balamurugan\desktop\clipsnet_vs_2015\clipsclrwrapper\source\clips\</FILEPATH>
        <FILENAME>exprnpsr.c</FILENAME>
        <LINE>296</LINE>
        <COLUMN>44</COLUMN>
        <KEYEVENT>
          <ID>10</ID>
          <KIND>usage</KIND>
          <IMPORTANCE>Essential</IMPORTANCE>
          <MESSAGE>'theFunction' is dereferenced, but may still be NULL</MESSAGE>
        </KEYEVENT>
      </SFA>
    </PATH>
  </DEFECT>
  <DEFECT>
    <SFA>
      <FILEPATH>c:\users\akshaya balamurugan\desktop\clipsnet_vs_2015\clipsclrwrapper\source\clips\</FILEPATH>
      <FILENAME>exprnpsr.c</FILENAME>
      <LINE>411</LINE>
      <COLUMN>9</COLUMN>
    </SFA>
    <DEFECTCODE>6305</DEFECTCODE>
    <DESCRIPTION>Potential mismatch between sizeof and countof quantities. Use sizeof() to scale byte sizes.</DESCRIPTION>
    <FUNCTION>PushRtnBrkContexts</FUNCTION>
    <DECORATED>?PushRtnBrkContexts@@$$FYAXPAX@Z</DECORATED>
    <FUNCLINE>406</FUNCLINE>
    <PROBABILITY>1</PROBABILITY>
    <RANK>2</RANK>
    <CATEGORY>
      <RULECATEGORY>mspft</RULECATEGORY>
    </CATEGORY>
    <PATH>
      <SFA>
        <FILEPATH>c:\users\akshaya balamurugan\desktop\clipsnet_vs_2015\clipsclrwrapper\source\clips\</FILEPATH>
        <FILENAME>exprnpsr.c</FILENAME>
        <LINE>409</LINE>
        <COLUMN>19</COLUMN>
      </SFA>
      <SFA>
        <FILEPATH>c:\users\akshaya balamurugan\desktop\clipsnet_vs_2015\clipsclrwrapper\source\clips\</FILEPATH>
        <FILENAME>exprnpsr.c</FILENAME>
        <LINE>411</LINE>
        <COLUMN>9</COLUMN>
        <KEYEVENT>
          <ID>1</ID>
          <KIND>usage</KIND>
          <IMPORTANCE>Essential</IMPORTANCE>
          <MESSAGE>Expression mixes element counts and byte quantities</MESSAGE>
        </KEYEVENT>
      </SFA>
    </PATH>
  </DEFECT>
  <DEFECT>
    <SFA>
      <FILEPATH>c:\users\akshaya balamurugan\desktop\clipsnet_vs_2015\clipsclrwrapper\source\clips\</FILEPATH>
      <FILENAME>exprnpsr.c</FILENAME>
      <LINE>431</LINE>
      <COLUMN>3</COLUMN>
    </SFA>
    <DEFECTCODE>6305</DEFECTCODE>
    <DESCRIPTION>Potential mismatch between sizeof and countof quantities. Use sizeof() to scale byte sizes.</DESCRIPTION>
    <FUNCTION>PopRtnBrkContexts</FUNCTION>
    <DECORATED>?PopRtnBrkContexts@@$$FYAXPAX@Z</DECORATED>
    <FUNCLINE>422</FUNCLINE>
    <PROBABILITY>1</PROBABILITY>
    <RANK>2</RANK>
    <CATEGORY>
      <RULECATEGORY>mspft</RULECATEGORY>
    </CATEGORY>
    <PATH>
      <SFA>
        <FILEPATH>c:\users\akshaya balamurugan\desktop\clipsnet_vs_2015\clipsclrwrapper\source\clips\</FILEPATH>
        <FILENAME>exprnpsr.c</FILENAME>
        <LINE>425</LINE>
        <COLUMN>19</COLUMN>
      </SFA>
      <SFA>
        <FILEPATH>c:\users\akshaya balamurugan\desktop\clipsnet_vs_2015\clipsclrwrapper\source\clips\</FILEPATH>
        <FILENAME>exprnpsr.c</FILENAME>
        <LINE>427</LINE>
        <COLUMN>41</COLUMN>
      </SFA>
      <SFA>
        <FILEPATH>c:\users\akshaya balamurugan\desktop\clipsnet_vs_2015\clipsclrwrapper\source\clips\</FILEPATH>
        <FILENAME>exprnpsr.c</FILENAME>
        <LINE>428</LINE>
        <COLUMN>40</COLUMN>
      </SFA>
      <SFA>
        <FILEPATH>c:\users\akshaya balamurugan\desktop\clipsnet_vs_2015\clipsclrwrapper\source\clips\</FILEPATH>
        <FILENAME>exprnpsr.c</FILENAME>
        <LINE>429</LINE>
        <COLUMN>9</COLUMN>
      </SFA>
      <SFA>
        <FILEPATH>c:\users\akshaya balamurugan\desktop\clipsnet_vs_2015\clipsclrwrapper\source\clips\</FILEPATH>
        <FILENAME>exprnpsr.c</FILENAME>
        <LINE>430</LINE>
        <COLUMN>38</COLUMN>
      </SFA>
      <SFA>
        <FILEPATH>c:\users\akshaya balamurugan\desktop\clipsnet_vs_2015\clipsclrwrapper\source\clips\</FILEPATH>
        <FILENAME>exprnpsr.c</FILENAME>
        <LINE>431</LINE>
        <COLUMN>3</COLUMN>
      </SFA>
      <SFA>
        <FILEPATH>c:\users\akshaya balamurugan\desktop\clipsnet_vs_2015\clipsclrwrapper\source\clips\</FILEPATH>
        <FILENAME>exprnpsr.c</FILENAME>
        <LINE>431</LINE>
        <COLUMN>3</COLUMN>
        <KEYEVENT>
          <ID>1</ID>
          <KIND>usage</KIND>
          <IMPORTANCE>Essential</IMPORTANCE>
          <MESSAGE>Expression mixes element counts and byte quantities</MESSAGE>
        </KEYEVENT>
      </SFA>
    </PATH>
  </DEFECT>
  <DEFECT>
    <SFA>
      <FILEPATH>c:\users\akshaya balamurugan\desktop\clipsnet_vs_2015\clipsclrwrapper\source\clips\</FILEPATH>
      <FILENAME>exprnpsr.c</FILENAME>
      <LINE>431</LINE>
      <COLUMN>3</COLUMN>
    </SFA>
    <DEFECTCODE>6305</DEFECTCODE>
    <DESCRIPTION>Potential mismatch between sizeof and countof quantities. Use sizeof() to scale byte sizes.</DESCRIPTION>
    <FUNCTION>PopRtnBrkContexts</FUNCTION>
    <DECORATED>?PopRtnBrkContexts@@$$FYAXPAX@Z</DECORATED>
    <FUNCLINE>422</FUNCLINE>
    <PROBABILITY>1</PROBABILITY>
    <RANK>2</RANK>
    <CATEGORY>
      <RULECATEGORY>mspft</RULECATEGORY>
    </CATEGORY>
    <PATH>
      <SFA>
        <FILEPATH>c:\users\akshaya balamurugan\desktop\clipsnet_vs_2015\clipsclrwrapper\source\clips\</FILEPATH>
        <FILENAME>exprnpsr.c</FILENAME>
        <LINE>425</LINE>
        <COLUMN>19</COLUMN>
      </SFA>
      <SFA>
        <FILEPATH>c:\users\akshaya balamurugan\desktop\clipsnet_vs_2015\clipsclrwrapper\source\clips\</FILEPATH>
        <FILENAME>exprnpsr.c</FILENAME>
        <LINE>427</LINE>
        <COLUMN>41</COLUMN>
      </SFA>
      <SFA>
        <FILEPATH>c:\users\akshaya balamurugan\desktop\clipsnet_vs_2015\clipsclrwrapper\source\clips\</FILEPATH>
        <FILENAME>exprnpsr.c</FILENAME>
        <LINE>428</LINE>
        <COLUMN>40</COLUMN>
      </SFA>
      <SFA>
        <FILEPATH>c:\users\akshaya balamurugan\desktop\clipsnet_vs_2015\clipsclrwrapper\source\clips\</FILEPATH>
        <FILENAME>exprnpsr.c</FILENAME>
        <LINE>429</LINE>
        <COLUMN>9</COLUMN>
      </SFA>
      <SFA>
        <FILEPATH>c:\users\akshaya balamurugan\desktop\clipsnet_vs_2015\clipsclrwrapper\source\clips\</FILEPATH>
        <FILENAME>exprnpsr.c</FILENAME>
        <LINE>430</LINE>
        <COLUMN>38</COLUMN>
      </SFA>
      <SFA>
        <FILEPATH>c:\users\akshaya balamurugan\desktop\clipsnet_vs_2015\clipsclrwrapper\source\clips\</FILEPATH>
        <FILENAME>exprnpsr.c</FILENAME>
        <LINE>431</LINE>
        <COLUMN>3</COLUMN>
      </SFA>
      <SFA>
        <FILEPATH>c:\users\akshaya balamurugan\desktop\clipsnet_vs_2015\clipsclrwrapper\source\clips\</FILEPATH>
        <FILENAME>exprnpsr.c</FILENAME>
        <LINE>431</LINE>
        <COLUMN>3</COLUMN>
        <KEYEVENT>
          <ID>1</ID>
          <KIND>usage</KIND>
          <IMPORTANCE>Essential</IMPORTANCE>
          <MESSAGE>Expression mixes element counts and byte quantities</MESSAGE>
        </KEYEVENT>
      </SFA>
    </PATH>
  </DEFECT>
  <DEFECT>
    <SFA>
      <FILEPATH>c:\users\akshaya balamurugan\desktop\clipsnet_vs_2015\clipsclrwrapper\source\clips\</FILEPATH>
      <FILENAME>exprnpsr.c</FILENAME>
      <LINE>476</LINE>
      <COLUMN>14</COLUMN>
    </SFA>
    <DEFECTCODE>6330</DEFECTCODE>
    <DESCRIPTION>'char' passed as _Param_(1) when 'unsigned char' is required in call to 'isdigit'.</DESCRIPTION>
    <FUNCTION>CheckExpressionAgainstRestrictions</FUNCTION>
    <DECORATED>?CheckExpressionAgainstRestrictions@@$$FYAHPAXPAUexpr@@PBD2@Z</DECORATED>
    <FUNCLINE>440</FUNCLINE>
    <PATH></PATH>
  </DEFECT>
  <DEFECT>
    <SFA>
      <FILEPATH>c:\users\akshaya balamurugan\desktop\clipsnet_vs_2015\clipsclrwrapper\source\clips\</FILEPATH>
      <FILENAME>exprnpsr.c</FILENAME>
      <LINE>488</LINE>
      <COLUMN>14</COLUMN>
    </SFA>
    <DEFECTCODE>6330</DEFECTCODE>
    <DESCRIPTION>'char' passed as _Param_(1) when 'unsigned char' is required in call to 'isdigit'.</DESCRIPTION>
    <FUNCTION>CheckExpressionAgainstRestrictions</FUNCTION>
    <DECORATED>?CheckExpressionAgainstRestrictions@@$$FYAHPAXPAUexpr@@PBD2@Z</DECORATED>
    <FUNCLINE>440</FUNCLINE>
    <PATH></PATH>
  </DEFECT>
</DEFECTS>